__init__.py
azerbaijani/__init__.py
azerbaijani/config.py
azerbaijani/detect.py
azerbaijani/test.py
tests/__init__.py
tests/test_detect.py
azerbaijani-0.1.1.dist-info/LICENSE
azerbaijani-0.1.1.dist-info/METADATA
azerbaijani-0.1.1.dist-info/WHEEL
azerbaijani-0.1.1.dist-info/top_level.txt
azerbaijani-0.1.1.dist-info/RECORD
