Metadata-Version: 2.1
Name: azerbaijani
Version: 0.1.1
Summary: Utility package for Azerbaijani
Author-email: Jafar Isbarov <cefer.isbarov@gmail.com>
Project-URL: Homepage, https://github.com/ceferisbarov/azerbaijani
Project-URL: Issues, https://github.com/ceferisbarov/azerbaijani/issues
Classifier: Programming Language :: Python :: 3
Classifier: License :: OSI Approved :: MIT License
Classifier: Operating System :: OS Independent
Requires-Python: >=3.8
License-File: LICENSE
